demonlist/__init__.py
pydemonlistapi-0.9.0.dist-info/licenses/LICENSE
pydemonlistapi-0.9.0.dist-info/METADATA
pydemonlistapi-0.9.0.dist-info/WHEEL
pydemonlistapi-0.9.0.dist-info/top_level.txt
pydemonlistapi-0.9.0.dist-info/RECORD
