Metadata-Version: 2.4
Name: pyDemonlistAPI
Version: 0.9.0
Summary: An python library that simply provides Global List API to your code.
Author-email: karelskiy127 <karjalanchel@gmail.com>, XBOCTATUK <xboctatuk213@gmail.com>
Project-URL: Homepage, https://github.com/CoolJayfather/pyDemonlistAPI
Project-URL: Issues, https://github.com/CoolJayfather/pyDemonlistAPI/issues
Classifier: Programming Language :: Python :: 3
Classifier: License :: OSI Approved :: MIT License
Classifier: Operating System :: OS Independent
Requires-Python: >=3.8
License-File: LICENSE
Dynamic: license-file
